<?xml version="1.0" encoding="UTF-8"?>
<metadata xml:lang="de"><Esri><CreaDate>20170214</CreaDate><CreaTime>11205400</CreaTime><ArcGISFormat>1.0</ArcGISFormat><SyncOnce>TRUE</SyncOnce><ModDate>20170214</ModDate><ModTime>174945</ModTime></Esri><dataIdInfo><idCitation><resTitle>TbxZentrenBearbeitenn</resTitle></idCitation></dataIdInfo><distInfo><distributor><distorFormat><formatName>ArcToolbox Tool</formatName></distorFormat></distributor></distInfo><tool name="TbxZentrenBearbeitenn" displayname="TbxZentrenBearbeitenn" toolboxalias=""><parameters/></tool></metadata>
